canvaslms/Makefile
canvaslms/__init__.py
canvaslms/cli/Makefile
canvaslms/cli/__init__.py
canvaslms/cli/assignments.nw
canvaslms/cli/assignments.py
canvaslms/cli/cache.nw
canvaslms/cli/cache.py
canvaslms/cli/calendar.nw
canvaslms/cli/calendar.py
canvaslms/cli/canvas_calendar.py
canvaslms/cli/cli.nw
canvaslms/cli/content.nw
canvaslms/cli/content.py
canvaslms/cli/courses.nw
canvaslms/cli/courses.py
canvaslms/cli/discussions.nw
canvaslms/cli/discussions.py
canvaslms/cli/grade.nw
canvaslms/cli/grade.py
canvaslms/cli/login.nw
canvaslms/cli/login.py
canvaslms/cli/modules.nw
canvaslms/cli/modules.py
canvaslms/cli/pages.nw
canvaslms/cli/pages.py
canvaslms/cli/quizzes.nw
canvaslms/cli/quizzes.py
canvaslms/cli/results.nw
canvaslms/cli/results.py
canvaslms/cli/results.py.broken
canvaslms/cli/submissions.nw
canvaslms/cli/submissions.py
canvaslms/cli/test content.py
canvaslms/cli/users.nw
canvaslms/cli/users.py
canvaslms/cli/utils.nw
canvaslms/cli/utils.py
canvaslms/grades/Makefile
canvaslms/grades/__init__.py
canvaslms/grades/conjunctavg.nw
canvaslms/grades/conjunctavg.py
canvaslms/grades/conjunctavgsurvey.nw
canvaslms/grades/conjunctavgsurvey.py
canvaslms/grades/disjunctmax.nw
canvaslms/grades/disjunctmax.py
canvaslms/grades/grades.nw
canvaslms/grades/grades.py
canvaslms/grades/maxgradesurvey.nw
canvaslms/grades/maxgradesurvey.py
canvaslms/grades/participation.nw
canvaslms/grades/participation.py
canvaslms/grades/tilkryLAB1.nw
canvaslms/grades/tilkryLAB1.py
canvaslms/hacks/Makefile
canvaslms/hacks/__init__.py
canvaslms/hacks/attachment_cache.nw
canvaslms/hacks/attachment_cache.py
canvaslms/hacks/canvasapi.nw
canvaslms/hacks/canvasapi.py
canvaslms/hacks/test_hacks.py
canvaslms-5.9.dist-info/METADATA
canvaslms-5.9.dist-info/WHEEL
canvaslms-5.9.dist-info/entry_points.txt
canvaslms-5.9.dist-info/licenses/LICENSE
canvaslms-5.9.dist-info/RECORD
