Metadata-Version: 2.4
Name: canvaslms
Version: 5.9
Summary: Command-line interface to Canvas LMS
License-Expression: MIT
License-File: LICENSE
Author: Daniel Bosk
Author-email: daniel@bosk.se
Maintainer: Daniel Bosk
Maintainer-email: dbosk@kth.se
Requires-Python: >=3.8
Classifier: Programming Language :: Python :: 3
Classifier: License :: OSI Approved :: MIT License
Classifier: Operating System :: OS Independent
Classifier: Environment :: Console
Classifier: Intended Audience :: Education
Classifier: Intended Audience :: Science/Research
Classifier: Topic :: Utilities
Provides-Extra: diff
Provides-Extra: llm
Requires-Dist: appdirs (>=1.4.4)
Requires-Dist: argcomplete (>=2,<4)
Requires-Dist: arrow (>=1.2.3)
Requires-Dist: cachetools (>=5.3.1)
Requires-Dist: canvasapi (>=3.4.0,<4.0.0)
Requires-Dist: keyring (>=24.2,<26.0)
Requires-Dist: llm (>=0.16) ; (python_version >= "3.9") and (extra == "llm")
Requires-Dist: llm-anthropic (>=0.19,<0.20) ; (python_version >= "3.9") and (extra == "llm")
Requires-Dist: llm-azure (>=1.1,<2.0) ; (python_version >= "3.9") and (extra == "llm")
Requires-Dist: llm-gemini (>=0.26.1,<0.27.0) ; (python_version >= "3.9") and (extra == "llm")
Requires-Dist: llm-github-copilot (>=0.3.1,<1.0.0) ; (python_version >= "3.9") and (extra == "llm")
Requires-Dist: llm-openai-plugin (>=0.7,<0.8) ; (python_version >= "3.9") and (extra == "llm")
Requires-Dist: llm-python (>=0.1,<0.2) ; (python_version >= "3.9") and (extra == "llm")
Requires-Dist: patiencediff (>=0.2.18,<0.3.0) ; (python_version >= "3.9") and (extra == "diff")
Requires-Dist: pypandoc (>=1.11)
Requires-Dist: pyyaml (>=5.1)
Requires-Dist: rich (>=13,<15)
Project-URL: Bug Tracker, https://github.com/dbosk/canvaslms/issues
Project-URL: Documentation, https://github.com/dbosk/canvaslms/releases
Project-URL: Repository, https://github.com/dbosk/canvaslms
